tests
dta
